{
  "build": "h57928b3_0",
  "build_number": 0,
  "channel": "https://conda.anaconda.org/conda-forge/win-64",
  "constrains": [],
  "depends": [
    "dotnet-aspnetcore 7.0.0 h91493d7_0",
    "dotnet-desktop 7.0.0 h57928b3_0",
    "dotnet-runtime 7.0.0 h91493d7_0",
    "dotnet-sdk 7.0.100 h91493d7_0"
  ],
  "extracted_package_dir": "C:\\Users\\runes\\anaconda3\\pkgs\\dotnet-7.0.100-h57928b3_0",
  "features": "",
  "files": [],
  "fn": "dotnet-7.0.100-h57928b3_0.tar.bz2",
  "license": "MIT",
  "license_family": "MIT",
  "link": {
    "source": "C:\\Users\\runes\\anaconda3\\pkgs\\dotnet-7.0.100-h57928b3_0",
    "type": 3
  },
  "md5": "505e8257514ac927644dc50b3e74856c",
  "name": "dotnet",
  "package_tarball_full_path": "C:\\Users\\runes\\anaconda3\\pkgs\\dotnet-7.0.100-h57928b3_0.tar.bz2",
  "paths_data": {
    "paths": [],
    "paths_version": 1
  },
  "requested_spec": "None",
  "sha256": "d3fd0ecb98a41a4bfb41c66990c34b2a2c43271c3314bdc86e761a1e9889978a",
  "size": 16701,
  "subdir": "win-64",
  "timestamp": 1668227332052,
  "track_features": "",
  "url": "https://conda.anaconda.org/conda-forge/win-64/dotnet-7.0.100-h57928b3_0.tar.bz2",
  "version": "7.0.100"
}